{
    "chosen_volume": "Tall (30in x 32in x 36in)",
    "cims": 5,
    "drive_train": "West coast",
    "height": 36,
    "last_modified": 1490290634912,
    "length": 32,
    "max_hopper_load": 20,
    "notes": "",
    "programming_language": "Labview",
    "robot_picture_default": 0,
    "robot_pictures": [
        {
            "filepath": "/data/user/0/frc3824.rohawkticsscouting2017/files/2017tnkn/robot_pictures/6517_0.jpg",
            "url": ""
        }
    ],
    "scout_name": "Abigail Bradfield",
    "team_number": 6517,
    "weight": 0,
    "width": 30
}